calendarcli/__init__.py
calendarcli/__mian__.py
calendar_cli_kku-2.0.0.dist-info/LICENSE
calendar_cli_kku-2.0.0.dist-info/METADATA
calendar_cli_kku-2.0.0.dist-info/WHEEL
calendar_cli_kku-2.0.0.dist-info/entry_points.txt
calendar_cli_kku-2.0.0.dist-info/top_level.txt
calendar_cli_kku-2.0.0.dist-info/RECORD
