Metadata-Version: 2.1
Name: calendar-cli-kku
Version: 2.0.0
Summary: test file
Home-page: https://github.com/VillSource/calendar-cli
License: UNKNOWN
Platform: UNKNOWN
License-File: LICENSE
Requires-Dist: rich
Requires-Dist: typer
Requires-Dist: inquirer
Requires-Dist: eel
Requires-Dist: julian
Requires-Dist: tzlocal
Requires-Dist: monthdelta
Requires-Dist: google-api-python-client
Requires-Dist: google-auth-httplib2
Requires-Dist: google-auth-oauthlib
